{
  "sectionId": "ecosistema",
  "sectionTitle": "Nuestros Productos",
  "sectionLede": "Tres líneas comerciales — Soluciones de Negocio, Plataformas SaaS y Servicios Profesionales — con página, flyer y canal de captación propio.",
  "odooNote": "Easy Odoo: somos <strong>consultores independientes</strong> sobre <strong>Odoo</strong>.",
  "categories": [
    {
      "id": "soluciones",
      "title": "Soluciones de Negocio",
      "grid": "duo",
      "products": [
        {
          "slug": "easy-odoo",
          "kicker": "Solución · Prioridad comercial",
          "title": "Easy Odoo",
          "description": "Implementación, soporte y desarrollo sobre Odoo.",
          "featuresLabel": "Servicios",
          "features": ["ERP", "Inventario", "Ventas", "Compras", "Contabilidad", "CxC / CxP", "Facturación electrónica", "Reportes gerenciales"],
          "image": "assets/images/flyers/easy-odoo.png",
          "visualStyle": "tarjeta",
          "pageHref": "soluciones.html",
          "pageLinkLabel": "Ver solución",
          "ctaPrimary": { "label": "Solicitar demostración", "href": "agenda.html" }
        },
        {
          "slug": "facturacion-electronica",
          "kicker": "Solución · Panamá",
          "title": "Facturación Electrónica Panamá",
          "description": "Implementación y soporte para empresas panameñas.",
          "featuresLabel": "Incluye",
          "features": ["Factura fiscal", "Nota de crédito", "Consumidor final", "Integración ERP", "Cumplimiento DGI"],
          "image": "assets/images/flyers/facturacion-electronica.png",
          "visualStyle": "tarjeta",
          "pageHref": "facturacion-electronica.html",
          "pageLinkLabel": "Ver solución",
          "ctaPrimary": {
            "label": "Solicitar información",
            "href": "https://wa.me/50766884938?text=Quiero%20informaci%C3%B3n%20sobre%20Facturaci%C3%B3n%20Electr%C3%B3nica%20Panam%C3%A1%20con%20EasyTech",
            "external": true
          }
        }
      ]
    },
    {
      "id": "plataformas",
      "title": "Plataformas SaaS",
      "grid": "default",
      "products": [
        {
          "slug": "easynodeone",
          "kicker": "Plataforma · En producción",
          "title": "EasyNodeOne (EN1)",
          "description": "Plataforma de membresías, eventos, citas, ventas y comunidades.",
          "featuresLabel": "Casos de uso",
          "features": ["Asociaciones", "Cámaras", "Colegios profesionales", "Institutos", "Organizaciones"],
          "image": "assets/images/flyers/en1-1.png",
          "imageFallback": "assets/images/logo-easynodeone.svg",
          "variant": "easynodeone",
          "featured": true,
          "pageHref": "easynodeone.html",
          "pageLinkLabel": "Ver plataforma",
          "ctaPrimary": {
            "label": "Crear cuenta",
            "href": "https://appprd.easynodeone.com/register",
            "external": true
          }
        },
        {
          "slug": "easy-converso",
          "kicker": "Plataforma · En producción",
          "title": "Easy Converso",
          "description": "Asistente inteligente para atención y automatización.",
          "featuresLabel": "Casos de uso",
          "features": ["Atención al cliente", "Soporte interno", "Captura de leads", "Automatización de consultas"],
          "image": "assets/images/logo-econverso.svg",
          "variant": "econverso",
          "pageHref": "econverso.html",
          "pageLinkLabel": "Ver plataforma",
          "ctaPrimary": { "label": "Solicitar demostración", "href": "agenda.html" }
        },
        {
          "slug": "eclassone",
          "kicker": "Plataforma · IA educativa",
          "title": "EClassOne",
          "description": "Plataforma educativa con IA para exámenes, material didáctico y analítica académica.",
          "featuresLabel": "Incluye",
          "features": ["Generador de exámenes", "Calificación inteligente", "Material didáctico", "Analítica educativa"],
          "image": "assets/images/eclassone/eclassone-hero.png",
          "variant": "eclassone",
          "pageHref": "eclassone.html",
          "pageLinkLabel": "Ver plataforma",
          "ctaPrimary": {
            "label": "Solicitar demostración",
            "href": "https://wa.me/50766884938?text=Quiero%20una%20demostraci%C3%B3n%20de%20EClassOne%20%E2%80%94%20EasyTech",
            "external": true
          }
        },
        {
          "slug": "ethesisone",
          "kicker": "Plataforma · Easy Thesis",
          "title": "Easy Thesis",
          "description": "Plataforma integral de gestión del ciclo de tesis para universidades.",
          "featuresLabel": "Incluye",
          "features": ["Expediente único", "Workflow académico", "Gestión documental", "Trazabilidad"],
          "image": "assets/images/easythesis/hero-portada.png",
          "imageFallback": "assets/images/easythesis/logo-horizontal.png",
          "variant": "ethesisone",
          "pageHref": "ethesisone.html",
          "pageLinkLabel": "Ver plataforma",
          "ctaPrimary": {
            "label": "Solicitar demostración",
            "href": "mailto:info@easytech.services?subject=Solicitud%20de%20demostraci%C3%B3n%20%E2%80%94%20Easy%20Thesis",
            "external": true
          }
        },
        {
          "slug": "eposone",
          "kicker": "Plataforma · Punto de venta",
          "title": "EPOSOne",
          "description": "Punto de venta simple, rápido y poderoso para retail, restaurantes y servicios.",
          "featuresLabel": "Incluye",
          "features": ["Ventas", "Inventario", "Clientes", "Reportes", "Online y offline"],
          "image": "assets/images/eposone/hero-card.png",
          "imageFallback": "assets/images/flyers/eposone.png",
          "variant": "eposone",
          "pageHref": "eposone.html",
          "pageLinkLabel": "Ver plataforma",
          "ctaPrimary": {
            "label": "Solicitar demostración",
            "href": "https://wa.me/50766884938?text=Quiero%20una%20demostraci%C3%B3n%20de%20EPOSOne%20%E2%80%94%20EasyTech",
            "external": true
          }
        },
        {
          "slug": "epayroll",
          "kicker": "Plataforma · Próximamente",
          "title": "EPayRoll",
          "description": "Planilla laboral configurable para Panamá — motor de cálculo, vacaciones programadas, CSS/DGI y liquidación.",
          "featuresLabel": "Incluye",
          "features": ["Motor de cálculo", "Vacaciones programadas", "Liquidación laboral", "CSS / DGI / SIPE", "Asistencia y turnos", "Integración contable"],
          "image": "assets/images/epayroll/hero-card.png",
          "imageFallback": "assets/images/flyers/epayroll.png",
          "variant": "epayroll",
          "soon": true,
          "pageHref": "epayroll.html",
          "pageLinkLabel": "Conocer más"
        }
      ]
    },
    {
      "id": "servicios",
      "title": "Servicios Profesionales",
      "grid": "duo",
      "products": [
        {
          "slug": "desarrollo-software",
          "kicker": "Servicio profesional · Desarrollo de Software",
          "title": "Desarrollo de Software a la Medida",
          "description": "Aplicaciones personalizadas conectadas al ecosistema EasyTech para impulsar la transformación digital de su organización.",
          "featuresLabel": "Incluye",
          "features": ["Apps web", "Apps móviles", "APIs", "Automatización e IA", "SaaS en la nube", "Dashboards"],
          "visualStyle": "tarjeta",
          "image": "assets/images/flyers/desarrollo-software.png",
          "imageFallback": "assets/images/desarrollo-software/flyer-full.png",
          "variant": "desarrollo-software",
          "pageHref": "desarrollo-software.html",
          "pageLinkLabel": "Ver casos de uso",
          "ctaPrimary": {
            "label": "Solicitar asesoría",
            "href": "https://wa.me/50766884938?text=Solicito%20asesor%C3%ADa%20de%20Desarrollo%20de%20Software%20%E2%80%94%20EasyTech",
            "external": true
          }
        },
        {
          "slug": "consultoria-ti",
          "kicker": "Servicio profesional",
          "title": "Consultoría TI",
          "description": "Acompañamiento estratégico para adoptar el ecosistema con criterio.",
          "featuresLabel": "Incluye",
          "features": ["Transformación digital", "Arquitectura empresarial", "Gobierno TI", "Estrategia tecnológica"],
          "visualStyle": "tarjeta",
          "image": "assets/images/flyers/consultoria-ti.png",
          "imageFallback": "assets/images/consultoria-ti/flyer-full.png",
          "pageHref": "consultoria-ti.html",
          "pageLinkLabel": "Ver servicio",
          "ctaPrimary": {
            "label": "Hablar con un consultor",
            "href": "https://wa.me/50766884938?text=Consulta%20sobre%20consultor%C3%ADa%20TI%20con%20EasyTech",
            "external": true
          }
        }
      ]
    }
  ]
}
